pykumaapi/__init__.py
pykumaapi/pykumaapi.py
pykumaapi-0.0.2.dist-info/LICENSE
pykumaapi-0.0.2.dist-info/METADATA
pykumaapi-0.0.2.dist-info/WHEEL
pykumaapi-0.0.2.dist-info/top_level.txt
pykumaapi-0.0.2.dist-info/RECORD
