Metadata-Version: 2.1
Name: pykumaapi
Version: 0.0.2
Summary: A package to connect KUMA (SIEM)
Home-page: https://github.com/arthurkondakov/pykumaapi/
Author: Artur Kondakov
Author-email: arthurkondakov@yandex.ru
License: UNKNOWN
Platform: UNKNOWN
Classifier: Programming Language :: Python :: 3.10
Classifier: License :: OSI Approved :: GNU General Public License v3 (GPLv3)
License-File: LICENSE
Requires-Dist: certifi (>=2022)
Requires-Dist: charset-normalizer (>=3)
Requires-Dist: idna (>=3)
Requires-Dist: requests (>=2.28)
Requires-Dist: urllib3 (>=1.26)
